<?xml version="1.0" encoding="UTF-8"?>
<cus:Customizations xmlns:cus="http://www.bea.com/wli/config/customizations" xmlns:xsi="http://www.w3.org/2001/XMLSchema-instance" xmlns:xt="http://www.bea.com/wli/config/xmltypes">
  <cus:customization xsi:type="cus:EnvValueCustomizationType">
    <cus:description/>
    <cus:envValueAssignments>
      <xt:envValueType>Service URI Table</xt:envValueType>
      <xt:location xsi:nil="true"/>
      <xt:owner>
        <xt:type>BusinessService</xt:type>
        <!--
                    THIS PATH should be updated to reflect <ALSBProject>/<folder>/<ALSB Business Service>
        -->
        <xt:path>ManageDigitalAccountDetails_1_0/businessservices/Account</xt:path>
      </xt:owner>
      <xt:value>
        <tran:tableElement xmlns:tran="http://www.bea.com/wli/sb/transports">
           <!--
                    THIS URL REPRESENTS THE ACTUAL URL FOR AN ENVIRONMENT (Applied to the ALSB Business Service)
            -->
          <tran:URI>https://www.google.co.in</tran:URI>
          <tran:weight>0</tran:weight>
        </tran:tableElement>
      </xt:value>
    </cus:envValueAssignments>
  </cus:customization>
     

</cus:Customizations>